MANIFEST.in
README.rst
setup.py
DisplayNode/DisplayNodeProxy.py
DisplayNode/DisplayNodeServer.py
DisplayNode/__init__.py
DisplayNode.egg-info/PKG-INFO
DisplayNode.egg-info/SOURCES.txt
DisplayNode.egg-info/dependency_links.txt
DisplayNode.egg-info/top_level.txt
DisplayNode/examples/__init__.py
DisplayNode/examples/examples.py
DisplayNode/tests/__init__.py
DisplayNode/tests/test_all.py