Metadata-Version: 1.1
Name: DisplayNode
Version: 0.2.0
Summary: Web-based plotting and data visualisation package.
Home-page: http://www.occiput.io/
Author: Stefano Pedemonte
Author-email: stefano.pedemonte@gmail.com
License: LICENSE.txt
Platform: UNKNOWN
Classifier: Programming Language :: Python
Classifier: Development Status :: 4 - Beta
Classifier: Environment :: Other Environment
Classifier: Intended Audience :: Science/Research
Classifier: License :: OSI Approved :: BSD License
Classifier: Operating System :: OS Independent
